paquete/__init__.py
paquete/adios/__init__.py
paquete/adios/despedida.py
paquete/hola/__init__.py
paquete/hola/saludos.py
tests/__init__.py
tests/test_hola.py
Paquete_JMPoo-5.0.dist-info/LICENSE
Paquete_JMPoo-5.0.dist-info/METADATA
Paquete_JMPoo-5.0.dist-info/WHEEL
Paquete_JMPoo-5.0.dist-info/top_level.txt
Paquete_JMPoo-5.0.dist-info/RECORD
