Metadata-Version: 2.1
Name: Paquete-JMPoo
Version: 5.0
Summary: Un paquete de saludo y despedida
Home-page: https://www.jmpoo.dev
Author: JMPoo
Author-email: jmpoo@gmail.dev
Classifier: Environment :: Console
Classifier: Intended Audience :: Developers
Classifier: License :: OSI Approved :: MIT License
Classifier: Operating System :: OS Independent
Classifier: Programming Language :: Python
Classifier: Topic :: Utilities
License-File: LICENSE
Requires-Dist: numpy (>=1.23.0)
